spotify/__init__.py
spotify/http.py
spotifypy-0.0.2.dist-info/LICENSE
spotifypy-0.0.2.dist-info/METADATA
spotifypy-0.0.2.dist-info/WHEEL
spotifypy-0.0.2.dist-info/top_level.txt
spotifypy-0.0.2.dist-info/RECORD
