Metadata-Version: 2.1
Name: spotifypy
Version: 0.0.2
Summary: ('No', 'description')
Home-page: UNKNOWN
Author: MrWalrus
Author-email: UNKNOWN
License: MIT
Platform: UNKNOWN
Classifier: Programming Language :: Python :: 3
Classifier: License :: OSI Approved :: MIT License
